json_worker/__init__.py
json_worker/json_worker.py
json_worker-0.0.4.dist-info/METADATA
json_worker-0.0.4.dist-info/WHEEL
json_worker-0.0.4.dist-info/top_level.txt
json_worker-0.0.4.dist-info/RECORD
