Metadata-Version: 2.1
Name: json-worker
Version: 0.0.4
Summary: Json worker
Home-page: https://github.com/automatethem/json-worker
Author: Sang Ki Kwon
Author-email: automatethem@gmail.com
License: MIT
Platform: UNKNOWN
Requires-Dist: python-supporter
Requires-Dist: ai-supporter
